[
    {
        "academic_year": "2021-2022",
        "institution": "MINISTERIO DE EDUCACIÓN",
        "title": "RESOLUCIÓN DE LA SECRETARÍA DE ESTADO DE EDUCACIÓN, POR LA QUE SE CONVOCAN BECAS DE CARÁCTER GENERAL PARA EL CURSO ACADÉMICO 2021-2022, PARA ESTUDIANTES QUE CURSEN ESTUDIOS POSTOBLIGATORIOS El Real Decreto 1721/2007, de 21 de diciembre, estableció un nuevo régimen de las becas y ayudas al estudio del Ministerio de Educación y Formación Profesional, modificando el anteriormente vigente de gestión centralizada y regulando, con carácter básico, los parámetros precisos para asegurar la igualdad en el acceso a las citadas becas y ayudas al estudio sin detrimento de las competencias normativas y de ejecución de las comunidades autónomas",
        "deadlines": [
            [
                "01/09/2021",
                "31/12/2021"
            ]
        ],
        "amounts": [
            "1.700,00 euros",
            "1.600,00 euros",
            "300,00 euros",
            "442,00 euros",
            "623,00 euros",
            "888,00 euros",
            "525,00 euros"
        ]
    },
    {
        "academic_year": "2022-2023",
        "institution": "MINISTERIO DE EDUCACIÓN Y FORMACIÓN PROFESIONAL RESOLUCIÓN DE LA SECRETARÍA DE ESTADO DE EDUCACIÓN",
        "title": "RESOLUCIÓN DE LA SECRETARÍA DE ESTADO DE EDUCACIÓN, POR LA QUE SE CONVOCAN BECAS DE CARÁCTER GENERAL PARA EL CURSO ACADÉMICO 2022-2023 PARA ESTUDIANTES QUE CURSEN ESTUDIOS POSTOBLIGATORIOS El Real Decreto 1721/2007, de 21 de diciembre, estableció un nuevo régimen de las becas y ayudas al estudio del Ministerio de Educación y Formación Profesional, modificando el anteriormente vigente de gestión centralizada y regulando, con carácter básico, los parámetros precisos para asegurar la igualdad en el acceso a las citadas becas y ayudas al estudio sin detrimento de las competencias normativas y de ejecución de las comunidades autónomas",
        "deadlines": [
            [
                "01/12/2022",
                "31/12/2022"
            ]
        ],
        "amounts": [
            "1.700,00 euros",
            "1.600,00 euros",
            "300,00 euros",
            "442,00 euros",
            "623,00 euros",
            "888,00 euros",
            "525,00 euros"
        ]
    },
    {
        "academic_year": "2023-2024",
        "institution": "MINISTERIO DE EDUCACIÓN Y FORMACIÓN PROFESIONAL RESOLUCIÓN DE LA SECRETARÍA DE ESTADO DE EDUCACIÓN",
        "title": "RESOLUCIÓN DE LA SECRETARÍA DE ESTADO DE EDUCACIÓN, POR LA QUE SE CONVOCAN BECAS DE CARÁCTER GENERAL PARA EL CURSO ACADÉMICO 2023-2024 PARA ESTUDIANTES QUE CURSEN ESTUDIOS POSTOBLIGATORIOS El Real Decreto 1721/2007, de 21 de diciembre, estableció un nuevo régimen de las becas y ayudas al estudio del Ministerio de Educación y Formación Profesional, modificando el anteriormente vigente de gestión centralizada y regulando, con carácter básico, los parámetros precisos para asegurar la igualdad en el acceso a las citadas becas y ayudas al estudio sin detrimento de las competencias normativas y de ejecución de las comunidades autónomas",
        "deadlines": [
            [
                "30/09/2023",
                "31/12/2023"
            ]
        ],
        "amounts": [
            "1.700,00 euros",
            "2.500,00 euros",
            "300,00 euros",
            "442,00 euros",
            "623,00 euros",
            "888,00 euros",
            "525,00 euros"
        ]
    },
    {
        "academic_year": "2024-2025",
        "institution": "MINISTERIO DE EDUCACIÓN",
        "title": "RESOLUCIÓN DE LA SECRETARÍA DE ESTADO DE EDUCACIÓN, POR LA QUE SE CONVOCAN BECAS DE CARÁCTER GENERAL PARA EL CURSO ACADÉMICO 2024-2025 PARA ESTUDIANTES QUE CURSEN ESTUDIOS POSTOBLIGATORIOS",
        "deadlines": [
            [
                "30/09/2024",
                "31/12/2024"
            ]
        ],
        "amounts": [
            "1.700,00 euros",
            "2.500,00 euros",
            "300,00 euros",
            "442,00 euros",
            "623,00 euros",
            "888,00 euros",
            "525,00 euros"
        ]
    },
    {
        "academic_year": "2025-2026",
        "institution": "MINISTERIO DE EDUCACIÓN",
        "title": "RESOLUCIÓN DE LA SECRETARÍA DE ESTADO DE EDUCACIÓN, POR LA QUE SE CONVOCAN BECAS DE CARÁCTER GENERAL PARA EL CURSO ACADÉMICO 2025-2026 PARA ESTUDIANTES QUE CURSEN ESTUDIOS POSTOBLIGATORIOS",
        "deadlines": [
            [
                "30/09/2025",
                "31/12/2025"
            ]
        ],
        "amounts": [
            "1.700,00 euros",
            "2.700,00 euros",
            "300,00 euros",
            "442,00 euros",
            "623,00 euros",
            "888,00 euros",
            "525,00 euros"
        ]
    }
]